LICENSE
migrations_graph/__init__.py
migrations_graph/admin.py
migrations_graph/apps.py
migrations_graph/models.py
migrations_graph/templates/migrations_graph/index.html
migrations_graph/tests.py
migrations_graph/urls.py
migrations_graph/views.py
django_migration_dependencies-0.1.4.dist-info/LICENSE
django_migration_dependencies-0.1.4.dist-info/WHEEL
django_migration_dependencies-0.1.4.dist-info/METADATA
django_migration_dependencies-0.1.4.dist-info/RECORD
