Metadata-Version: 2.1
Name: django-migration-dependencies
Version: 0.1.4
Summary: A Django app to visualise the migrations graph
Home-page: https://github.com/edg956/django-migration-dependencies
License: MIT
Author: Eugenio Doñaque
Author-email: eugenio@donaque.xyz
Requires-Python: >=3.8,<4.0
Classifier: License :: OSI Approved :: MIT License
Classifier: Programming Language :: Python :: 3
Classifier: Programming Language :: Python :: 3.8
Classifier: Programming Language :: Python :: 3.9
Classifier: Programming Language :: Python :: 3.10
Classifier: Programming Language :: Python :: 3.11
Project-URL: Repository, https://github.com/edg956/django-migration-dependencies
